design.sv
`timescale 1ns / 1ps
module parking_system( 
                input clk,reset_n,
 input sensor_entrance, sensor_exit, 
 input [1:0] password_1, password_2,
 output wire GREEN_LED,RED_LED,
 output reg [6:0] HEX_1, HEX_2
    );
 parameter IDLE = 3'b000, WAIT_PASSWORD = 3'b001, WRONG_PASS = 3'b010, RIGHT_PASS = 3'b011,STOP = 3'b100;
 
  
 reg[2:0] current_state, next_state;
 reg[31:0] counter_wait;
 reg red_tmp,green_tmp;
 
  
 always @(posedge clk or negedge reset_n)
 begin
 if(~reset_n) 
 current_state = IDLE;
 else
 current_state = next_state;
 end
 
  
 always @(posedge clk or negedge reset_n) 
 begin
 if(~reset_n) 
 counter_wait <= 0;
 else if(current_state==WAIT_PASSWORD)
 counter_wait <= counter_wait + 1;
 else 
 counter_wait <= 0;
 end
 
  
 always @(*)
 begin
 case(current_state)
 IDLE: begin
         if(sensor_entrance == 1)
 next_state = WAIT_PASSWORD;
 else
 next_state = IDLE;
 end
 WAIT_PASSWORD: begin
 if(counter_wait <= 3)
 next_state = WAIT_PASSWORD;
 else 
 begin
 if((password_1==2'b01)&&(password_2==2'b10))
 next_state = RIGHT_PASS;
 else
 next_state = WRONG_PASS;
 end
 end
 WRONG_PASS: begin
 if((password_1==2'b01)&&(password_2==2'b10))
 next_state = RIGHT_PASS;
 else
 next_state = WRONG_PASS;
 end
 RIGHT_PASS: begin
 if(sensor_entrance==1 && sensor_exit == 1)
 next_state = STOP;
 else if(sensor_exit == 1)
 next_state = IDLE;
 else
 next_state = RIGHT_PASS;
 end
 STOP: begin
 if((password_1==2'b01)&&(password_2==2'b10))
 next_state = RIGHT_PASS;
 else
 next_state = STOP;
 end
 default: next_state = IDLE;
 endcase
 end
 
  
 always @(posedge clk) begin 
 case(current_state)
 IDLE: begin
 green_tmp = 1'b0;
 red_tmp = 1'b0;
 HEX_1 = 7'b1111111; // off
 HEX_2 = 7'b1111111; // off
 end
 WAIT_PASSWORD: begin
 green_tmp = 1'b0;
 red_tmp = 1'b1;
 HEX_1 = 7'b000_0110; // E
 HEX_2 = 7'b010_1011; // n 
 end
 WRONG_PASS: begin
 green_tmp = 1'b0;
 red_tmp = ~red_tmp;
 HEX_1 = 7'b000_0110; // E
 HEX_2 = 7'b000_0110; // E 
 end
 RIGHT_PASS: begin
 green_tmp = ~green_tmp;
 red_tmp = 1'b0;
 HEX_1 = 7'b000_0010; // 6
 HEX_2 = 7'b100_0000; // 0 
 end
 STOP: begin
 green_tmp = 1'b0;
 red_tmp = ~red_tmp;
 HEX_1 = 7'b001_0010; // 5
 HEX_2 = 7'b000_1100; // P 
 end
 endcase
 end
 assign RED_LED = red_tmp  ;
 assign GREEN_LED = green_tmp;

endmodule

testbench.sv
`timescale 1ns / 1ps
module tb_parking_system;

  
  reg clk=0;
  reg reset_n;
  reg sensor_entrance;
  reg sensor_exit;
  reg [1:0] password_1;
  reg [1:0] password_2;

  
  wire GREEN_LED;
  wire RED_LED;
  wire [6:0] HEX_1;
  wire [6:0] HEX_2;
  
  
  parking_system uut (
  .clk(clk), 
    .reset_n(reset_n), 
  .sensor_entrance(sensor_entrance), 
  .sensor_exit(sensor_exit), 
    .password_1(password_1), 
    .password_2(password_2), 
  .GREEN_LED(GREEN_LED), 
  .RED_LED(RED_LED), 
  .HEX_1(HEX_1), 
 .HEX_2(HEX_2)
 );

initial
  begin
    clk=1'b0;
    forever
      #10 clk=~clk;
   end
  
  
 initial begin
 
   
 reset_n = 0;
 sensor_entrance = 1;
 sensor_exit = 1;
 password_1 = 0;
 password_2 = 0;
 
   reset_n = 1;
 #20;
 sensor_entrance = 1;
 #1000;
 sensor_entrance = 0;
 password_1 = 1;
 password_2 = 2;
 #2000;
 sensor_exit =1;
  
 end 
initial
  begin
    #5000 $finish;
  end
initial begin
  $dumpfile("dump.vcd");
  $dumpvars(1);
end
endmodule

dump.vcd
$date
	Tue Nov 23 06:44:01 2021
$end
$version
	Icarus Verilog
$end
$timescale
	1ps
$end
$scope module tb_parking_system $end
$var wire 1 ! RED_LED $end
$var wire 7 " HEX_2 [6:0] $end
$var wire 7 # HEX_1 [6:0] $end
$var wire 1 $ GREEN_LED $end
$var reg 1 % clk $end
$var reg 2 & password_1 [1:0] $end
$var reg 2 ' password_2 [1:0] $end
$var reg 1 ( reset_n $end
$var reg 1 ) sensor_entrance $end
$var reg 1 * sensor_exit $end
$upscope $end
$enddefinitions $end
#0
$dumpvars
1*
1)
1(
b0 '
b0 &
0%
x$
bx #
bx "
x!
$end
#10000
b1111111 "
b1111111 #
0!
0$
1%
#20000
0%
#30000
b101011 "
b110 #
1!
1%
#40000
0%
#50000
1%
#60000
0%
#70000
1%
#80000
0%
#90000
1%
#100000
0%
#110000
1%
#120000
0%
#130000
b110 "
0!
1%
#140000
0%
#150000
1!
1%
#160000
0%
#170000
0!
1%
#180000
0%
#190000
1!
1%
#200000
0%
#210000
0!
1%
#220000
0%
#230000
1!
1%
#240000
0%
#250000
0!
1%
#260000
0%
#270000
1!
1%
#280000
0%
#290000
0!
1%
#300000
0%
#310000
1!
1%
#320000
0%
#330000
0!
1%
#340000
0%
#350000
1!
1%
#360000
0%
#370000
0!
1%
#380000
0%
#390000
1!
1%
#400000
0%
#410000
0!
1%
#420000
0%
#430000
1!
1%
#440000
0%
#450000
0!
1%
#460000
0%
#470000
1!
1%
#480000
0%
#490000
0!
1%
#500000
0%
#510000
1!
1%
#520000
0%
#530000
0!
1%
#540000
0%
#550000
1!
1%
#560000
0%
#570000
0!
1%
#580000
0%
#590000
1!
1%
#600000
0%
#610000
0!
1%
#620000
0%
#630000
1!
1%
#640000
0%
#650000
0!
1%
#660000
0%
#670000
1!
1%
#680000
0%
#690000
0!
1%
#700000
0%
#710000
1!
1%
#720000
0%
#730000
0!
1%
#740000
0%
#750000
1!
1%
#760000
0%
#770000
0!
1%
#780000
0%
#790000
1!
1%
#800000
0%
#810000
0!
1%
#820000
0%
#830000
1!
1%
#840000
0%
#850000
0!
1%
#860000
0%
#870000
1!
1%
#880000
0%
#890000
0!
1%
#900000
0%
#910000
1!
1%
#920000
0%
#930000
0!
1%
#940000
0%
#950000
1!
1%
#960000
0%
#970000
0!
1%
#980000
0%
#990000
1!
1%
#1000000
0%
#1010000
0!
1%
#1020000
0%
b10 '
b1 &
0)
#1030000
b1000000 "
b10 #
1$
1%
#1040000
0%
#1050000
b1111111 "
b1111111 #
0$
1%
